dualcode/__init__.py
dualcode/variable.py
dualcode/variables.py
dualcode-2.0.0.dist-info/LICENCE
dualcode-2.0.0.dist-info/METADATA
dualcode-2.0.0.dist-info/WHEEL
dualcode-2.0.0.dist-info/top_level.txt
dualcode-2.0.0.dist-info/RECORD
