Metadata-Version: 2.2
Name: dualcode
Version: 2.0.0
Summary: A package to manage variables in a JSON file
Author: Maximiliano David Sanchez
Author-email: maximilianosanchez1304@gmail.com
License: IST
Classifier: Programming Language :: Python :: 3
Classifier: License :: OSI Approved :: MIT License
Classifier: Operating System :: OS Independent
License-File: LICENCE
Dynamic: author
Dynamic: author-email
Dynamic: classifier
Dynamic: description
Dynamic: description-content-type
Dynamic: license
Dynamic: summary
